README.md
setup.py
LiftoffTools.egg-info/PKG-INFO
LiftoffTools.egg-info/SOURCES.txt
LiftoffTools.egg-info/dependency_links.txt
LiftoffTools.egg-info/entry_points.txt
LiftoffTools.egg-info/requires.txt
LiftoffTools.egg-info/top_level.txt
liftofftools/__init__.py
liftofftools/alignment.py
liftofftools/annotation.py
liftofftools/cli_arguments.py
liftofftools/filepaths.py
liftofftools/liftofftools.py
liftofftools/sequences.py
liftofftools/subprocesses.py
liftofftools/test_parasail.py
liftofftools/cluster_analysis/__init__.py
liftofftools/cluster_analysis/analyze_clusters.py
liftofftools/cluster_analysis/clusters.py
liftofftools/cluster_analysis/mmseqs_workflow.py
liftofftools/synteny/__init__.py
liftofftools/synteny/plot_gene_order.py
liftofftools/synteny/synteny.py
liftofftools/tests/__init__.py
liftofftools/variants/__init__.py
liftofftools/variants/variants.py